ninepatch/__init__.py
ninepatch/commands/__init__.py
ninepatch/commands/ninepatch.py
ninepatch/commands/ninepatch_viewer.py
ninepatch-0.2.0.dist-info/LICENSE
ninepatch-0.2.0.dist-info/METADATA
ninepatch-0.2.0.dist-info/WHEEL
ninepatch-0.2.0.dist-info/entry_points.txt
ninepatch-0.2.0.dist-info/top_level.txt
ninepatch-0.2.0.dist-info/RECORD
