Metadata-Version: 2.1
Name: ninepatch
Version: 0.2.0
Summary: Slice and scale 9-patch images
Author-email: Thomas Schüßler <vindolin@gmail.com>
Project-URL: Homepage, https://github.com/vindolin/ninepatch
Classifier: Programming Language :: Python :: 3
Classifier: License :: OSI Approved :: MIT License
Classifier: Operating System :: OS Independent
Requires-Python: >=3.9
License-File: LICENSE
Requires-Dist: pillow
